LICENSE
simple_graphql/__init__.py
simple_graphql/auth/__init__.py
simple_graphql/auth/apps.py
simple_graphql/auth/auth.py
simple_graphql/auth/exceptions.py
simple_graphql/auth/middleware.py
simple_graphql/auth/migrations/0001_initial.py
simple_graphql/auth/migrations/__init__.py
simple_graphql/auth/models.py
simple_graphql/auth/mutations.py
simple_graphql/django/__init__.py
simple_graphql/django/config.py
simple_graphql/django/fields/__init__.py
simple_graphql/django/fields/authorize.py
simple_graphql/django/fields/connection.py
simple_graphql/django/fields/exceptions.py
simple_graphql/django/fields/inputs.py
simple_graphql/django/fields/node.py
simple_graphql/django/middleware.py
simple_graphql/django/schema/__init__.py
simple_graphql/django/schema/builder.py
simple_graphql/django/schema/exceptions.py
simple_graphql/django/schema/node.py
simple_graphql/django/schema/query.py
simple_graphql/django/schema/schema.py
simple_graphql/django/schema/utils.py
simple_graphql/django/search.py
simple_graphql/django/types.py
django_simple_graphql-0.5.0.dist-info/LICENSE
django_simple_graphql-0.5.0.dist-info/WHEEL
django_simple_graphql-0.5.0.dist-info/METADATA
django_simple_graphql-0.5.0.dist-info/RECORD
