Metadata-Version: 2.1
Name: django-simple-graphql
Version: 0.5.0
Summary: A stupid simple GraphQL setup for Django
Home-page: https://github.com/JoaRiski/django-simple-graphql
License: MIT
Author: Joa Riski
Author-email: joa.riski@riskidev.fi
Requires-Python: >=3.8,<4.0
Classifier: License :: OSI Approved :: MIT License
Classifier: Programming Language :: Python :: 3
Classifier: Programming Language :: Python :: 3.8
Classifier: Programming Language :: Python :: 3.9
Requires-Dist: django-filter (>=2.4.0,<3.0.0)
Requires-Dist: graphene-django (>=2.15.0,<3.0.0)
Project-URL: Repository, https://github.com/JoaRiski/django-simple-graphql
